idae/__init__.py
idae/__main__.py
idae/cli.py
idae/dependencies.py
idae/pep723.py
idae/py.typed
idae/resolver.py
idae/venv.py
idae-1.1.0.dist-info/LICENSE.txt
idae-1.1.0.dist-info/METADATA
idae-1.1.0.dist-info/WHEEL
idae-1.1.0.dist-info/entry_points.txt
idae-1.1.0.dist-info/RECORD
