Metadata-Version: 2.1
Name: idae
Version: 1.1.0
Summary: A PEP 772 implementation
Home-page: https://github.com/ThatXliner/idae
License: GPL-3.0-or-later
Keywords: script,cli,python,typer
Author: Bryan Hu
Author-email: thatxliner@gmail.com
Requires-Python: >=3.8,<4.0
Classifier: Development Status :: 5 - Production/Stable
Classifier: License :: OSI Approved :: GNU General Public License v3 or later (GPLv3+)
Classifier: Natural Language :: English
Classifier: Operating System :: OS Independent
Classifier: Programming Language :: Python :: 3
Classifier: Programming Language :: Python :: 3.8
Classifier: Programming Language :: Python :: 3.9
Classifier: Programming Language :: Python :: 3.10
Classifier: Programming Language :: Python :: 3.11
Classifier: Programming Language :: Python :: 3.12
Classifier: Programming Language :: Python :: Implementation :: CPython
Classifier: Typing :: Typed
Requires-Dist: findpython (>=0.4.0,<0.5.0)
Requires-Dist: packaging (>=23.2)
Requires-Dist: platformdirs (>=4.0.0)
Requires-Dist: tomli (>=2.0.1,<3.0.0) ; python_version < "3.11"
Requires-Dist: typer[all] (>=0.9.0,<0.10.0)
Requires-Dist: typing-extensions (>=4.8.0,<5.0.0) ; python_version < "3.9"
